mopidy_twitterdj
