Metadata-Version: 1.1
Name: Mopidy-TwitterDJ
Version: 0.1.4
Summary: Controls Spotify via Twitter
Home-page: https://github.com/lino/mopidy-twitterdj
Author: Lino Helms
Author-email: lino@lino.io
License: Apache License, Version 2.0
Platform: UNKNOWN
Classifier: Environment :: No Input/Output (Daemon)
Classifier: Intended Audience :: End Users/Desktop
Classifier: License :: OSI Approved :: Apache Software License
Classifier: Operating System :: OS Independent
Classifier: Programming Language :: Python :: 2
Classifier: Topic :: Multimedia :: Sound/Audio :: Players
